openseespy/__init__.py
openseespy/opensees/__init__.py
openseespy/postprocessing/ModelToJSON.py
openseespy/postprocessing/__init__.py
openseespy/preprocessing/DiscretizeMember.py
openseespy/preprocessing/__init__.py
pyFAST/__init__.py
pyFAST/common.py
pyFAST/airfoils/DynamicStall.py
pyFAST/airfoils/Polar.py
pyFAST/airfoils/__init__.py
pyFAST/airfoils/polar_file.py
pyFAST/airfoils/tests/__init__.py
pyFAST/airfoils/tests/test_polar_interp.py
pyFAST/airfoils/tests/test_polar_manip.py
pyFAST/airfoils/tests/test_polar_params.py
pyFAST/airfoils/tests/test_polar_subfunctions.py
pyFAST/airfoils/tests/test_run_Examples.py
pyFAST/case_generation/__init__.py
pyFAST/case_generation/case_gen.py
pyFAST/case_generation/runner.py
pyFAST/case_generation/tests/__init__.py
pyFAST/case_generation/tests/test_run_Examples.py
pyFAST/converters/__init__.py
pyFAST/converters/beam.py
pyFAST/converters/beamDynToHawc2.py
pyFAST/converters/beamdyn.py
pyFAST/converters/elastodyn.py
pyFAST/converters/hawc2.py
pyFAST/converters/hawc2ToBeamDyn.py
pyFAST/converters/hawc2ToElastoDyn.py
pyFAST/converters/hawc2ToOpenfast.py
pyFAST/converters/openfastToHawc2.py
pyFAST/converters/tests/__init__.py
pyFAST/converters/tests/test_K_BD_H2.py
pyFAST/converters/tests/test_beamprops.py
pyFAST/converters/tests/test_hawc2ToBeamDyn.py
pyFAST/converters/tests/test_run_Examples.py
pyFAST/fastfarm/AMRWindSimulation.py
pyFAST/fastfarm/FASTFarmCaseCreation.py
pyFAST/fastfarm/TurbSimCaseCreation.py
pyFAST/fastfarm/__init__.py
pyFAST/fastfarm/fastfarm.py
pyFAST/fastfarm/tests/__init__.py
pyFAST/fastfarm/tests/test_run_Examples.py
pyFAST/fastfarm/tests/test_turbsimExtent.py
pyFAST/input_output/__init__.py
pyFAST/input_output/amrwind_file.py
pyFAST/input_output/bladed_out_file.py
pyFAST/input_output/bmodes_out_file.py
pyFAST/input_output/cactus_element_file.py
pyFAST/input_output/cactus_file.py
pyFAST/input_output/converters.py
pyFAST/input_output/csv_file.py
pyFAST/input_output/excel_file.py
OpenFastSEES-3.5.1.dist-info/METADATA
OpenFastSEES-3.5.1.dist-info/WHEEL
OpenFastSEES-3.5.1.dist-info/entry_points.txt
OpenFastSEES-3.5.1.dist-info/top_level.txt
OpenFastSEES-3.5.1.dist-info/RECORD
