Metadata-Version: 2.1
Name: OpenFastSEES
Version: 3.5.1
Summary: Combined package of OpenSeesPy and pyFAST
Home-page: https://github.com/yourusername/OpenFastSEES
Classifier: Topic :: Utilities
Classifier: Topic :: Software Development :: Testing
Classifier: Development Status :: 4 - Beta
Classifier: Programming Language :: Python :: 3.6
Classifier: Programming Language :: Python :: 3.7
Classifier: Programming Language :: Python :: 3.8
Classifier: Programming Language :: Python :: 3.9
Classifier: Programming Language :: Python :: 3.10
Classifier: Topic :: Software Development :: Version Control :: Git
Requires-Python: >=3.6
Requires-Dist: matplotlib
Requires-Dist: openpyxl
Requires-Dist: numpy (>=1.15.2)
Requires-Dist: pandas
Requires-Dist: pyarrow
Requires-Dist: scipy
Requires-Dist: chardet
Requires-Dist: xarray
Requires-Dist: pytest
Requires-Dist: openseespy
